standby/__init__.py
standby/core.py
standby/env.py
standby/exc.py
standby/hint.py
standby/py.typed
standby_variables-1.1.0.dist-info/METADATA
standby_variables-1.1.0.dist-info/WHEEL
standby_variables-1.1.0.dist-info/licenses/LICENSE
standby_variables-1.1.0.dist-info/RECORD
