Metadata-Version: 2.4
Name: standby-variables
Version: 1.1.0
Summary: Dynamic variables for static namespaces
Project-URL: Homepage, https://github.com/ilia-khaustov/standby-variables
Project-URL: Repository, https://github.com/ilia-khaustov/standby-variables
Project-URL: Issues, https://github.com/ilia-khaustov/standby-variables/issues
Author: Ilia Khaustov
License: MIT License
License-File: LICENSE
Keywords: configuration,environment,typing,validation,variables
Classifier: Development Status :: 4 - Beta
Classifier: Intended Audience :: Developers
Classifier: License :: OSI Approved :: MIT License
Classifier: Programming Language :: Python :: 3
Classifier: Programming Language :: Python :: 3 :: Only
Classifier: Programming Language :: Python :: 3.11
Classifier: Programming Language :: Python :: 3.12
Classifier: Programming Language :: Python :: 3.13
Classifier: Programming Language :: Python :: 3.14
Classifier: Typing :: Typed
Requires-Python: >=3.11
Provides-Extra: dev
Requires-Dist: hatch; extra == 'dev'
Requires-Dist: hatchling; extra == 'dev'
Requires-Dist: isort; extra == 'dev'
Requires-Dist: mypy; extra == 'dev'
Requires-Dist: pytest; extra == 'dev'
Requires-Dist: pytest-cov; extra == 'dev'
Requires-Dist: ruff; extra == 'dev'
Requires-Dist: tox>=4; extra == 'dev'
